mothra/__about__.py
mothra/__init__.py
mothra-0.1.0.dist-info/METADATA
mothra-0.1.0.dist-info/WHEEL
mothra-0.1.0.dist-info/entry_points.txt
mothra-0.1.0.dist-info/licenses/LICENSE.txt
mothra-0.1.0.dist-info/RECORD
