Metadata-Version: 2.3
Name: mothra
Version: 0.1.0
Summary: PowerPoint lib
Project-URL: Documentation, https://daizutabi.github.io/mothra
Project-URL: Source, https://github.com/daizutabi/mothra
Project-URL: Issues, https://github.com/daizutabi/mothra/issues
Author-email: daizutabi <daizutabi@gmail.com>
License-Expression: MIT
License-File: LICENSE.txt
Classifier: Development Status :: 4 - Beta
Classifier: Framework :: MkDocs
Classifier: Programming Language :: Python
Classifier: Programming Language :: Python :: 3.10
Classifier: Programming Language :: Python :: 3.11
Classifier: Programming Language :: Python :: 3.12
Classifier: Topic :: Documentation
Classifier: Topic :: Software Development :: Documentation
Requires-Python: >=3.10
